README.md
setup.py
z_zytome.egg-info/PKG-INFO
z_zytome.egg-info/SOURCES.txt
z_zytome.egg-info/dependency_links.txt
z_zytome.egg-info/requires.txt
z_zytome.egg-info/top_level.txt
zytome/__init__.py
zytome/bridge/__init__.py
zytome/explorer/__init__.py
zytome/explorer/download.py
zytome/portal/__init__.py
zytome/portal/_interfaces/__init__.py
zytome/portal/_interfaces/dataset.py
zytome/portal/cellxgene/__init__.py
zytome/portal/cellxgene/base.py
zytome/portal/cellxgene/calandrelli_2020/__init__.py
zytome/portal/cellxgene/calandrelli_2020/scrna_seq_data_analysis_of_endothelium_enrinched_mesenteric_arterial_tissues_from_human_donors.py
zytome/portal/cellxgene/calandrelli_2020/scrna_seq_data_analysis_of_huvecs_treated_with_high_glucose_and_tnfalpha.py
zytome/portal/cellxgene/de_vrij_2024/__init__.py
zytome/portal/cellxgene/de_vrij_2024/cross_sectional.py
zytome/portal/cellxgene/de_vrij_2024/longitudinal.py
zytome/portal/cellxgene/dharshini_2024/__init__.py
zytome/portal/cellxgene/dharshini_2024/all_cells.py
zytome/portal/cellxgene/dharshini_2024/exhibitory.py
zytome/portal/cellxgene/dharshini_2024/inhibitory.py
zytome/portal/cellxgene/elmentaite_2021/__init__.py
zytome/portal/cellxgene/elmentaite_2021/total_cells_of_the_human_intestinal_tract_mapped_across_space_and_time.py
zytome/portal/cellxgene/fasolino_2022/__init__.py
zytome/portal/cellxgene/fasolino_2022/multiomics_single_cell_analysis_of_human_pancreatic_islets.py
zytome/portal/cellxgene/guimaraes_2024/__init__.py
zytome/portal/cellxgene/guimaraes_2024/a_multi_tissue_single_cell_tumor_microenvironment_atlas.py
zytome/portal/cellxgene/human_oral_and_craniofacial_cell_atlas/__init__.py
zytome/portal/cellxgene/human_oral_and_craniofacial_cell_atlas/oral_and_craniofacial_atlas.py
zytome/portal/cellxgene/muto_2021/__init__.py
zytome/portal/cellxgene/muto_2021/adult_human_kidney_atac.py
zytome/portal/cellxgene/muto_2021/adult_human_kidney_rna.py
zytome/portal/cellxgene/pan_2024/__init__.py
zytome/portal/cellxgene/pan_2024/full_dataset.py
zytome/portal/cellxgene/perez_2022/__init__.py
zytome/portal/cellxgene/perez_2022/multiplexed_scrna_seq_adult_lupus_samples.py
