Metadata-Version: 2.4
Name: z-zytome
Version: 0.0.57
Summary: Zytome is declarative library for handling gene expression data for various data portals or datasets.
Home-page: https://github.com/mzguntalan/zytome
Author: Marko Zolo Gozano Untalan
Author-email: mzguntalan@gmail.com
License: Apache-2.0
Classifier: Development Status :: 3 - Alpha
Classifier: Programming Language :: Python :: 3.11
Classifier: Programming Language :: Python :: 3.12
Classifier: Programming Language :: Python :: 3.13
Classifier: Programming Language :: Python :: 3.14
Requires-Dist: anndata>=0.12.1
Requires-Dist: numpy>=2.2.6
Dynamic: author
Dynamic: author-email
Dynamic: classifier
Dynamic: home-page
Dynamic: license
Dynamic: requires-dist
Dynamic: summary
